LICENSE
MANIFEST.in
README.rst
setup.cfg
setup.py
django_super_popups/__init__.py
django_super_popups.egg-info/PKG-INFO
django_super_popups.egg-info/SOURCES.txt
django_super_popups.egg-info/dependency_links.txt
django_super_popups.egg-info/not-zip-safe
django_super_popups.egg-info/top_level.txt
django_super_popups/static/super_popups/superpopups.css
django_super_popups/static/super_popups/superpopups.js